pywhapbot/__init__.py
pywhapbot/browsers.py
pywhapbot/install.py
pywhapbot/utils.py
pywhapbot/whapbot.py
pywhapbot-1.0.2.dist-info/LICENSE
pywhapbot-1.0.2.dist-info/METADATA
pywhapbot-1.0.2.dist-info/WHEEL
pywhapbot-1.0.2.dist-info/top_level.txt
pywhapbot-1.0.2.dist-info/RECORD
