Metadata-Version: 2.1
Name: pywhapbot
Version: 1.0.2
Summary: WhatsApp Web API Wrapper for Chrome, Firefox, Opera, Brave and Edge.
Home-page: https://github.com/saizk/pywhapbot
Author: saizk
Author-email: sergioaizcorbe@hotmail.com
License: UNKNOWN
Project-URL: Bug Tracker, https://github.com/saizk/pywhapbot/issues
Platform: UNKNOWN
Classifier: Programming Language :: Python :: 3
Classifier: Programming Language :: Python :: 3.6
Classifier: Programming Language :: Python :: 3.7
Classifier: Programming Language :: Python :: 3.8
Classifier: License :: OSI Approved :: MIT License
Classifier: Operating System :: OS Independent
Requires-Python: >=3.6
License-File: LICENSE
Requires-Dist: selenium (~=3.141.0)
Requires-Dist: msedge-selenium-tools (~=3.141.3)
